uiautomator2/__init__.py
uiautomator2/__main__.py
uiautomator2/_input.py
uiautomator2/_proto.py
uiautomator2/_selector.py
uiautomator2/abstract.py
uiautomator2/assets/.gitignore
uiautomator2/assets/app-uiautomator.apk
uiautomator2/assets/sync.sh
uiautomator2/assets/u2.jar
uiautomator2/assets/version.json
uiautomator2/base.py
uiautomator2/core.py
uiautomator2/exceptions.py
uiautomator2/ext/__init__.py
uiautomator2/ext/htmlreport/README.md
uiautomator2/ext/htmlreport/__init__.py
uiautomator2/ext/htmlreport/assets/index.html
uiautomator2/ext/htmlreport/assets/pig.jpg
uiautomator2/ext/htmlreport/assets/simplehttpserver.py
uiautomator2/ext/htmlreport/assets/start.bat
uiautomator2/ext/info/__init__.py
uiautomator2/ext/info/conf.py
uiautomator2/ext/perf/README.md
uiautomator2/ext/perf/__init__.py
uiautomator2/ext/perf/net.png
uiautomator2/ext/perf/summary.png
uiautomator2/image.py
uiautomator2/screenrecord.py
uiautomator2/settings.py
uiautomator2/swipe.py
uiautomator2/utils.py
uiautomator2/version.py
uiautomator2/watcher.py
uiautomator2/xpath.py
uiautomator2-3.4.1.dist-info/LICENSE
uiautomator2-3.4.1.dist-info/METADATA
uiautomator2-3.4.1.dist-info/WHEEL
uiautomator2-3.4.1.dist-info/entry_points.txt
uiautomator2-3.4.1.dist-info/RECORD
