Metadata-Version: 2.1
Name: uiautomator2
Version: 3.4.1
Summary: uiautomator for android device
Home-page: https://github.com/openatx/uiautomator2
License: MIT
Author: codeskyblue
Author-email: codeskyblue@gmail.com
Requires-Python: >=3.8,<4.0
Classifier: License :: OSI Approved :: MIT License
Classifier: Programming Language :: Python :: 3
Classifier: Programming Language :: Python :: 3.8
Classifier: Programming Language :: Python :: 3.9
Classifier: Programming Language :: Python :: 3.10
Classifier: Programming Language :: Python :: 3.11
Classifier: Programming Language :: Python :: 3.12
Classifier: Programming Language :: Python :: 3.13
Requires-Dist: Pillow
Requires-Dist: adbutils (>=2.9.3,<2.10.0)
Requires-Dist: importlib-resources ; python_version < "3.9"
Requires-Dist: lxml
Requires-Dist: requests
Requires-Dist: retry2 (>=0.9.5,<0.10.0)
